gpusnatcher/__init__.py
gpusnatcher/configs.py
gpusnatcher/emails.py
gpusnatcher/gpu.py
gpusnatcher/logger.py
gpusnatcher/main.py
gpusnatcher/utils.py
gpusnatcher-1.8.0.dist-info/WHEEL
gpusnatcher-1.8.0.dist-info/entry_points.txt
gpusnatcher-1.8.0.dist-info/METADATA
gpusnatcher-1.8.0.dist-info/RECORD
