Metadata-Version: 2.3
Name: gpusnatcher
Version: 1.8.0
Summary: A tool to find and snatch free GPUs on a shared server.
Author: Wilmer Wang
Author-email: Wilmer Wang <wangwei0206@foxmail.com>
Requires-Dist: rich>=14.1.0
Requires-Dist: tomli-w>=1.2.0
Requires-Dist: torch==2.8.0 ; extra == 'cpu'
Requires-Dist: torch==2.8.0 ; extra == 'cuda129'
Maintainer: Wilmer Wang
Maintainer-email: Wilmer Wang <wangwei0206@foxmail.com>
Requires-Python: >=3.12
Project-URL: Homepage, https://github.com/wilmerwang/GPUSnatcher
Provides-Extra: cpu
Provides-Extra: cuda129
